suid/__init__.py
suid-1.0.1.dist-info/LICENSE
suid-1.0.1.dist-info/METADATA
suid-1.0.1.dist-info/WHEEL
suid-1.0.1.dist-info/top_level.txt
suid-1.0.1.dist-info/RECORD
