Metadata-Version: 2.1
Name: suid
Version: 1.0.1
Summary: Generates sortable, date/time-containing, human friendly unique string IDs
Author-email: Anton Benderskiy <loderan@ruservice.ru>
License: MIT License
Project-URL: Homepage, https://github.com/ruanton/suid
Project-URL: Bug Tracker, https://github.com/ruanton/suid/issues
Keywords: python
Classifier: Programming Language :: Python :: 3
Classifier: License :: OSI Approved :: MIT License
Classifier: Operating System :: OS Independent
Requires-Python: >=3.8
License-File: LICENSE
Provides-Extra: testing
Requires-Dist: pytest ; extra == 'testing'
Requires-Dist: pytest-cov ; extra == 'testing'
